README.md
setup.py
TOPSIS_Chetan_101803440.egg-info/PKG-INFO
TOPSIS_Chetan_101803440.egg-info/SOURCES.txt
TOPSIS_Chetan_101803440.egg-info/dependency_links.txt
TOPSIS_Chetan_101803440.egg-info/entry_points.txt
TOPSIS_Chetan_101803440.egg-info/requires.txt
TOPSIS_Chetan_101803440.egg-info/top_level.txt
src/topsis.py